heurispy/__init__.py
heurispy/ayudantes.py
heurispy/framework.py
heurispy/problema.py
heurispy/recolector_resultados.py
heurispy/script_prueba_automatizada.py
heurispy/__pycache__/__init__.cpython-37.pyc
heurispy/__pycache__/ayudantes.cpython-37.pyc
heurispy/__pycache__/framework.cpython-37.pyc
heurispy/__pycache__/problema.cpython-37.pyc
heurispy/__pycache__/recolector_resultados.cpython-37.pyc
heurispy/ejemplos/problema de coloracion de grafos/__init__.py
heurispy/ejemplos/problema de coloracion de grafos/coloracion_grafo.py
heurispy/ejemplos/problema de coloracion de grafos/coloracion_grafo_bus_arm.py
heurispy/ejemplos/problema de coloracion de grafos/coloracion_grafo_rec_sim.py
"heurispy/ejemplos/problema de coloracion de grafos/Datos/BusquedaArmonica/2019-10-11---08-24/BusquedaArmonica-[50, 50, 0.6, 0.2]-0-2019-10-11---08-24.csv"
"heurispy/ejemplos/problema de coloracion de grafos/Datos/BusquedaArmonica/2019-10-11---08-24/BusquedaArmonica-[50, 50, 0.6, 0.2]-0-2019-10-11---08-24.txt"
"heurispy/ejemplos/problema de coloracion de grafos/Datos/BusquedaArmonica/2019-10-11---08-24/BusquedaArmonica-[50, 50, 0.6, 0.2]-1-2019-10-11---08-24.csv"
"heurispy/ejemplos/problema de coloracion de grafos/Datos/BusquedaArmonica/2019-10-11---08-24/BusquedaArmonica-[50, 50, 0.6, 0.2]-1-2019-10-11---08-24.txt"
"heurispy/ejemplos/problema de coloracion de grafos/Datos/BusquedaArmonica/2019-10-11---08-24/BusquedaArmonica-[50, 50, 0.6, 0.2]-2-2019-10-11---08-24.csv"
"heurispy/ejemplos/problema de coloracion de grafos/Datos/BusquedaArmonica/2019-10-11---08-24/BusquedaArmonica-[50, 50, 0.6, 0.2]-2-2019-10-11---08-24.txt"
"heurispy/ejemplos/problema de coloracion de grafos/Datos/BusquedaArmonica/2019-10-11---08-24/BusquedaArmonica-[50, 50, 0.6, 0.2]-3-2019-10-11---08-24.csv"
"heurispy/ejemplos/problema de coloracion de grafos/Datos/BusquedaArmonica/2019-10-11---08-24/BusquedaArmonica-[50, 50, 0.6, 0.2]-3-2019-10-11---08-24.txt"
heurispy-1.0.4.dist-info/LICENSE.txt
heurispy-1.0.4.dist-info/METADATA
heurispy-1.0.4.dist-info/WHEEL
heurispy-1.0.4.dist-info/top_level.txt
heurispy-1.0.4.dist-info/RECORD
