Metadata-Version: 2.1
Name: heurispy
Version: 1.0.4
Summary: Framework for heuristic exploration of local search heuristics in discrete optimization problems.
Home-page: https://gitlab.com/escamilla.een/heurispy
Author: Esteban Escamilla Navarro
Author-email: escamilla.een@gmail.com
License: Apache License, Version 2.0
Platform: UNKNOWN
Requires-Dist: pathos
Requires-Dist: tqdm
Requires-Dist: numpy
Requires-Dist: pandas
Requires-Dist: fpdf
Requires-Dist: matplotlib
Requires-Dist: pypdf2
Requires-Dist: xlrd
